markdown2image/__init__.py
markdown2image/async_api.py
markdown2image/sync_api.py
markdown2image-0.0.9.2.dist-info/LICENSE
markdown2image-0.0.9.2.dist-info/METADATA
markdown2image-0.0.9.2.dist-info/WHEEL
markdown2image-0.0.9.2.dist-info/top_level.txt
markdown2image-0.0.9.2.dist-info/RECORD
