Metadata-Version: 2.2
Name: markdown2image
Version: 0.0.9.2
Summary: Python utility to convert markdown and html to image
Author-email: PY-DNG <PY_DNG@126.com>
Project-URL: Homepage, https://github.com/PYUDNG/markdown2image
Project-URL: Issues, https://github.com/PYUDNG/markdown2image/issues
License-File: LICENSE
Requires-Dist: markdown
Requires-Dist: playwright
